BSD.txt
CHANGELOG
LICENSE.txt
MANIFEST.in
setup.cfg
setup.py
docs/about.html
docs/json.html
docs/toc.html
docs/xml.html
tests/about.py
tests/about.rst
tests/about_json.py
tests/about_xml.py
tests/json.rst
tests/test_json.py
tests/xml.rst
tests/functional/toc/toc.py
tests/functional/toc/toc.rst
trestle/__init__.py
trestle/json.py
trestle/plugin.py
trestle/xml.py
trestle.egg-info/PKG-INFO
trestle.egg-info/SOURCES.txt
trestle.egg-info/dependency_links.txt
trestle.egg-info/entry_points.txt
trestle.egg-info/requires.txt
trestle.egg-info/top_level.txt
trestle/css/rst.css