Metadata-Version: 1.0
Name: trestle
Version: 0.2
Summary: Trestle: doctest for ReST(ful services)
Home-page: http://code.google.com/p/nose-trestle/
Author: Jason Pellerin
Author-email: jpellerin@leapfrogonline.com
License: MIT License
Platform: UNKNOWN
Classifier: Development Status :: 3 - Alpha
Classifier: Intended Audience :: Developers
Classifier: License :: OSI Approved :: MIT License
Classifier: Topic :: Software Development :: Testing
